{
    "1": {
        "name": "Спектакль «Кадриль»",
        "groups": {
            "1-1": {
                "color": "rgb(31, 173, 173)",
                "price": 1250
            },
            "1-2": {
                "color": "rgb(71, 133, 133)",
                "price": 1450
            },
            "1-3": {
                "color": "rgb(204, 204, 0)",
                "price": 1650
            },
            "1-4": {
                "color": "rgb(173, 173, 31)",
                "price": 1850
            },
            "1-5": {
                "color": "rgb(133, 133, 71)",
                "price": 1950
            },
            "1-6": {
                "color": "rgb(204, 102, 0)",
                "price": 2050
            },
            "1-7": {
                "color": "rgb(173, 102, 31)",
                "price": 2250
            },
            "1-8": {
                "color": "rgb(133, 102, 71)",
                "price": 2350
            },
            "1-9": {
                "color": "rgb(204, 0, 0)",
                "price": 2550
            },
            "1-10": {
                "color": "rgb(173, 31, 31)",
                "price": 3050
            },
            "1-11": {
                "color": "rgb(133, 71, 71)",
                "price": 2750
            }
        }
    },
    "2": {
        "name": "Другой спектакль",
        "groups": {}
    }
}